pkJson/__init__.py
pkJson/_settings.py
pkJson/_utils.py
pkJson/_version.py
pkJson/cli.py
pkjson-2024.1.0rc3.dist-info/METADATA
pkjson-2024.1.0rc3.dist-info/WHEEL
pkjson-2024.1.0rc3.dist-info/entry_points.txt
pkjson-2024.1.0rc3.dist-info/top_level.txt
pkjson-2024.1.0rc3.dist-info/RECORD
