Metadata-Version: 2.1
Name: pkjson
Version: 2024.1.0rc3
Summary: pkJson used for compressing project to move between systems.
Author-email: "Robert J. DeWilde" <github@cyberneticinnovations.com>
License: MIT License
Classifier: License :: OSI Approved :: MIT License
Requires-Python: >=3.8
Requires-Dist: click >=8.1.7
Requires-Dist: loguru >=0.7.2
Requires-Dist: seversion >=2024.1.0
Requires-Dist: cryptography >=41.0.5
Requires-Dist: pydantic-settings >=2.1.0
